MarcoPolo/__init__.py
MarcoPolo/utils.py
MarcoPolo/regression/__init__.py
MarcoPolo/regression/datasets.py
MarcoPolo/regression/models.py
MarcoPolo/regression/trainer.py
MarcoPolo/summarization/__init__.py
MarcoPolo/summarization/summarizer.py
MarcoPolo/visualization/__init__.py
MarcoPolo/visualization/reporter.py
MarcoPolo/visualization/template/index.html
MarcoPolo/visualization/template/assets/details_close.png
MarcoPolo/visualization/template/assets/details_open.png
MarcoPolo/visualization/template/assets/mp.png
MarcoPolo/visualization/template/assets/mp_white.png
MarcoPolo/visualization/template/assets/mp_white_large_font.png
MarcoPolo/visualization/template/assets/scripts.js
MarcoPolo/visualization/template/assets/styles.css
MarcoPolo/visualization/template/assets/.ipynb_checkpoints/details_close-checkpoint.png
MarcoPolo/visualization/template/assets/.ipynb_checkpoints/details_open-checkpoint.png
MarcoPolo/visualization/template/assets/.ipynb_checkpoints/mp-checkpoint.png
MarcoPolo/visualization/template/assets/.ipynb_checkpoints/mp_white-checkpoint.png
MarcoPolo/visualization/template/assets/.ipynb_checkpoints/mp_white_large_font-checkpoint.png
marcopolo_pytorch-1.1.1.dist-info/LICENSE
marcopolo_pytorch-1.1.1.dist-info/METADATA
marcopolo_pytorch-1.1.1.dist-info/WHEEL
marcopolo_pytorch-1.1.1.dist-info/top_level.txt
marcopolo_pytorch-1.1.1.dist-info/RECORD
