Metadata-Version: 2.1
Name: marcopolo-pytorch
Version: 1.1.1
Summary: MarcoPolo: a method to discover differentially expressed genes in single-cell RNA-seq data without depending on prior clustering
Home-page: https://github.com/chanwkimlab/MarcoPolo
Author: Chanwoo Kim
Author-email: 
Keywords: single-cell,bioinformatics,pytorch
Classifier: Development Status :: 4 - Beta
Classifier: Intended Audience :: Developers
Classifier: Topic :: Scientific/Engineering :: Bio-Informatics
Classifier: Topic :: Scientific/Engineering :: Artificial Intelligence
Classifier: License :: Other/Proprietary License
Classifier: Programming Language :: Python :: 3.6
Classifier: Programming Language :: Python :: 3.7
Classifier: Programming Language :: Python :: 3.8
Classifier: Programming Language :: Python :: 3.9
License-File: LICENSE
Requires-Dist: tqdm
Requires-Dist: einops (>=0.3)
Requires-Dist: numpy (>=1.19.2)
Requires-Dist: torch (>=1.4.0)
Requires-Dist: pandas (>=1.2.0)
Requires-Dist: scikit-learn (>=0.24.1)
Requires-Dist: scipy (>=1.6.1)
Requires-Dist: matplotlib (>=3.3.0)
Requires-Dist: seaborn (>=0.11.1)
Requires-Dist: Jinja2 (>=2.11.2)
Requires-Dist: anndata (>=0.7.4)
Requires-Dist: rpy2 (>=3.4.2)
Requires-Dist: ipywidgets (>=7.5.1)
Requires-Dist: scanpy (>=1.9.0)
